PyGymFormat/ModuleContainers.py
PyGymFormat/ModuleGame.py
PyGymFormat/ModuleInvisible.py
PyGymFormat/ModulePlayer.py
PyGymFormat/ModuleRule.py
PyGymFormat/ModuleVisibles.py
PyGymFormat/__init__.py
pygymformat-0.0.2.dist-info/LICENSE
pygymformat-0.0.2.dist-info/METADATA
pygymformat-0.0.2.dist-info/WHEEL
pygymformat-0.0.2.dist-info/top_level.txt
pygymformat-0.0.2.dist-info/RECORD
