Metadata-Version: 2.1
Name: pygymformat
Version: 0.0.2
Summary: Base classes for making games that comply with Openai Gym environment creation standards
Home-page: https://github.com/Bassneptun/PyGymFormat
Author: Jeremy Neumann
Author-email: jeremytaylorneumann@gmail.com
License: MIT
License-File: LICENSE
Requires-Dist: pygame
Requires-Dist: numpy
Requires-Dist: vectormath
